carlosferreyra/__init__.py
carlosferreyra/__main__.py
carlosferreyra/actions.py
carlosferreyra/banner.py
carlosferreyra/card.py
carlosferreyra/config.json
carlosferreyra/config.py
carlosferreyra/menu.py
carlosferreyra/py.typed
carlosferreyra/utils.py
carlosferreyra-1.1.2.dist-info/WHEEL
carlosferreyra-1.1.2.dist-info/entry_points.txt
carlosferreyra-1.1.2.dist-info/METADATA
carlosferreyra-1.1.2.dist-info/RECORD
