Metadata-Version: 2.3
Name: carlosferreyra
Version: 1.1.2
Summary: Interactive CLI business card for Carlos Ferreyra
Author: Carlos Eduardo Ferreyra
Author-email: Carlos Eduardo Ferreyra <eduferreyraok@gmail.com>
Requires-Dist: click>=8.0.0
Requires-Dist: colorama>=0.4.0
Requires-Dist: inquirer>=3.0.0
Requires-Dist: pyfiglet>=1.0.0
Requires-Dist: rich>=13.0.0
Requires-Python: >=3.13
